{
  "name": "modal.scss",
  "type": "registry:style",
  "files": [
    {
      "target": "style/modal.scss",
      "content": "@use 'sass:map';\r\n\r\n@use './shared' as *;\r\n@use './design' as *;\r\n\r\n$modal: () !default;\r\n$modal: map.merge(\r\n  (\r\n    z-index: value('masker-z-index'),\r\n    bg-color: value('bg-color-base'),\r\n    radius: value('radius-base'),\r\n    s-color: value('shadow-color-base'),\r\n    shadow: value('shadow-shape') value('modal-s-color'),\r\n    d-color: value('border-color-light-2'),\r\n    title-font-size: value('font-size-primary'),\r\n    title-weight: 500,\r\n    title-color: value('content-color-primary'),\r\n    header-v-padding: 8px,\r\n    header-h-padding: 14px,\r\n    body-v-padding: 14px,\r\n    body-h-padding: 14px,\r\n    body-line-height: value('line-height-base'),\r\n    footer-v-padding: 10px,\r\n    footer-h-padding: 16px,\r\n    close-color: value('content-color-placeholder'),\r\n    close-color-hover: value('content-color-base'),\r\n    resizer-color: value('border-color-light-1')\r\n  ),\r\n  $modal\r\n);\r\n\r\n.#{$namespace}-modal {\r\n  &-vars {\r\n    @include define-preset-values('modal', $modal);\r\n  }\r\n\r\n  @include basis {\r\n    z-index: value('modal-z-index');\r\n  }\r\n\r\n  @include fixed;\r\n  @include inherit-color;\r\n\r\n  &--inner {\r\n    position: absolute;\r\n    overflow: hidden;\r\n  }\r\n\r\n  &__transform {\r\n    position: absolute;\r\n    inset: 0;\r\n    pointer-events: none;\r\n  }\r\n\r\n  &__wrapper {\r\n    position: absolute;\r\n    top: 100px;\r\n    display: flex;\r\n    flex-direction: column;\r\n    max-width: calc(100vw - 28px);\r\n    pointer-events: auto;\r\n    background-color: value('modal-bg-color');\r\n    border: 0;\r\n    border-radius: value('modal-radius');\r\n    box-shadow: value('modal-shadow');\r\n    transform: translateZ(0);\r\n\r\n    &--dragging,\r\n    &--resizing {\r\n      user-select: none;\r\n    }\r\n\r\n    &--dragging {\r\n      will-change: top, left;\r\n    }\r\n  }\r\n\r\n  &--inner &__wrapper {\r\n    position: absolute;\r\n  }\r\n\r\n  &__header {\r\n    position: relative;\r\n    display: flex;\r\n    flex-shrink: 0;\r\n    align-items: center;\r\n    padding: value('modal-header-v-padding') value('modal-header-h-padding');\r\n    border-bottom: value('border-shape') value('modal-d-color');\r\n  }\r\n\r\n  &--draggable &__header {\r\n    cursor: move;\r\n    user-select: none;\r\n  }\r\n\r\n  &--undivided &__header {\r\n    border-bottom: 0;\r\n  }\r\n\r\n  &__title {\r\n    flex: 1 0 0;\r\n    font-size: value('modal-title-font-size');\r\n    font-weight: value('modal-title-weight');\r\n    color: value('modal-title-color');\r\n  }\r\n\r\n  &__content {\r\n    position: relative;\r\n    flex: auto;\r\n    min-width: 0;\r\n    min-height: 0;\r\n    padding: value('modal-body-v-padding') value('modal-body-h-padding');\r\n    line-height: value('modal-body-line-height');\r\n  }\r\n\r\n  &__footer {\r\n    position: relative;\r\n    display: flex;\r\n    flex-shrink: 0;\r\n    align-items: center;\r\n    justify-content: flex-end;\r\n    padding: value('modal-footer-v-padding') value('modal-footer-h-padding');\r\n    border-top: value('border-shape') value('modal-d-color');\r\n  }\r\n\r\n  &--undivided &__footer {\r\n    border-top: 0;\r\n  }\r\n\r\n  &__close {\r\n    display: flex;\r\n    align-items: center;\r\n    height: 24px;\r\n    padding: 0;\r\n    margin-inline-start: 6px;\r\n    color: value('modal-close-color');\r\n    cursor: pointer;\r\n    background-color: transparent;\r\n    border: 0;\r\n    outline: 0;\r\n    transition: value('transition-color');\r\n\r\n    &:hover,\r\n    &:focus {\r\n      color: value('modal-close-color-hover');\r\n    }\r\n  }\r\n\r\n  &__resizer {\r\n    position: absolute;\r\n    right: 0;\r\n    bottom: 0;\r\n    width: 10px;\r\n    height: 10px;\r\n    cursor: nw-resize;\r\n    background-image: linear-gradient(\r\n      -45deg,\r\n      transparent calc(30% - 1px),\r\n      value('modal-resizer-color') 30%,\r\n      transparent calc(30% + 1px),\r\n      transparent calc(50% - 1px),\r\n      value('modal-resizer-color') 50%,\r\n      transparent calc(50% + 1px)\r\n    );\r\n    border-radius: 0 0 value('modal-radius');\r\n  }\r\n}\r\n"
    }
  ]
}
